{
  "project_info": {
    "project_number": "713071349956",
    "project_id": "newssharingapp-8f00a",
    "storage_bucket": "newssharingapp-8f00a.firebasestorage.app"
  },
  "client": [
    {
      "client_info": {
        "mobilesdk_app_id": "1:713071349956:android:6067ae21543530cc9ab991",
        "android_client_info": {
          "package_name": "ganesh.project.newssharingapp"
        }
      },
      "oauth_client": [],
      "api_key": [
        {
          "current_key": "AIzaSyAVbm-IKAHqY_9ihq-A9j4ZSaHHtKGzS9I"
        }
      ],
      "services": {
        "appinvite_service": {
          "other_platform_oauth_client": []
        }
      }
    }
  ],
  "configuration_version": "1"
}